SpotiTube/__init__.py
SpotiTube/song.py
SpotiTube/spotify.py
SpotiTube/youtube.py
SpotiTube-0.0.1.dist-info/METADATA
SpotiTube-0.0.1.dist-info/WHEEL
SpotiTube-0.0.1.dist-info/top_level.txt
SpotiTube-0.0.1.dist-info/RECORD
