Metadata-Version: 2.1
Name: SpotiTube
Version: 0.0.1
Summary: A package to download songs from Spotify using YouTube
Home-page: https://github.com/snehashish090/song_downloader
Author: Snehashish Laskar
Author-email: snehashishlaskar.dev@example.com
Classifier: Development Status :: 3 - Alpha
Classifier: Intended Audience :: Developers
Classifier: License :: OSI Approved :: MIT License
Classifier: Programming Language :: Python :: 3
Classifier: Programming Language :: Python :: 3.8
Classifier: Programming Language :: Python :: 3.9
Classifier: Programming Language :: Python :: 3.10
Requires-Python: >=3.8
Requires-Dist: requests >=2.25.1
Requires-Dist: pytube >=12.1.0
Requires-Dist: spotipy >=2.19.0
Requires-Dist: moviepy >=1.0.3
Requires-Dist: eyed3 >=0.9.5
Requires-Dist: pytubefix >=1.0.0
